{
  "domains": [
    "fmoh-echis",
    "fmoh-echis-staging",
    "fmoh-echis-link-test"
  ],
  "server_environment": [
    "production",
    "echis"
  ],
  "config": {
   "configured_indicators":[
      {
         "comment":null,
         "create_index":true,
         "display_name":"health_post_id",
         "datatype":"string",
         "expression":{
            "type":"root_doc",
            "expression":{
               "datatype":null,
               "type":"property_name",
               "property_name":"health_post_id"
            }
         },
         "transform":{

         },
         "is_primary_key":false,
         "is_nullable":true,
         "type":"expression",
         "column_id":"health_post_id"
      },
      {
         "comment":null,
         "create_index":false,
         "display_name":null,
         "datatype":"string",
         "type":"expression",
         "transform":{
         },
         "is_primary_key":false,
         "is_nullable":true,
         "expression":{
            "value_expression":{
               "datatype":null,
               "type":"property_name",
               "property_name":"name"
            },
            "type":"related_doc",
            "related_doc_type":"Location",
            "doc_id_expression":{
               "datatype":null,
               "type":"property_name",
               "property_name":"health_post_id"
            }
         },
         "column_id":"health_post_name"
      },
      {
         "comment":null,
         "create_index":false,
         "display_name":null,
         "datatype":"string",
         "expression":{
            "datatype":"string",
            "type":"property_name",
            "property_name":"village_name"
         },
         "transform":{

         },
         "is_primary_key":false,
         "is_nullable":true,
         "type":"expression",
         "column_id":"gote_name"
      },
      {
         "comment":null,
         "create_index":false,
         "display_name":null,
         "datatype":"integer",
         "expression":{
            "datatype":"integer",
            "test":{
               "operator":"eq",
               "type":"boolean_expression",
               "expression":{
                  "datatype":null,
                  "type":"property_name",
                  "property_name":"type"
               },
               "comment":null,
               "property_value":"family"
            },
            "type":"conditional",
            "expression_if_true":{
               "type":"constant",
               "constant":1
            },
            "expression_if_false":{
               "type":"constant",
               "constant":0
            }
         },
         "transform":{

         },
         "is_primary_key":false,
         "is_nullable":true,
         "type":"expression",
         "column_id":"household_count"
      },
      {
         "comment":null,
         "create_index":false,
         "display_name":null,
         "datatype":"integer",
         "type":"expression",
         "transform":{

         },
         "is_primary_key":false,
         "is_nullable":true,
         "expression":{
            "datatype":"integer",
            "test":{
               "type":"and",
               "filters":[
                  {
                     "operator":"eq",
                     "expression":{
                        "datatype":null,
                        "type":"property_name",
                        "property_name":"type"
                     },
                     "type":"boolean_expression",
                     "comment":null,
                     "property_value":"family"
                  },
                  {
                     "operator":"eq",
                     "expression":{
                        "datatype":null,
                        "type":"property_name",
                        "property_name":"separate_animal_house"
                     },
                     "type":"boolean_expression",
                     "comment":null,
                     "property_value":"yes"
                  }
               ]
            },
            "expression_if_false":{
               "constant":0,
               "type":"constant"
            },
            "type":"conditional",
            "expression_if_true":{
               "constant":1,
               "type":"constant"
            }
         },
         "column_id":"no_of_separate_animal_house"
      },
      {
         "comment":null,
         "create_index":false,
         "display_name":null,
         "datatype":"integer",
         "type":"expression",
         "transform":{

         },
         "is_primary_key":false,
         "is_nullable":true,
         "expression":{
            "datatype":"integer",
            "test":{
               "type":"and",
               "filters":[
                  {
                     "operator":"eq",
                     "expression":{
                        "datatype":null,
                        "type":"property_name",
                        "property_name":"type"
                     },
                     "type":"boolean_expression",
                     "comment":null,
                     "property_value":"family"
                  },
                  {
                     "operator":"eq",
                     "expression":{
                        "datatype":null,
                        "type":"property_name",
                        "property_name":"separate_kitchen"
                     },
                     "type":"boolean_expression",
                     "comment":null,
                     "property_value":"yes"
                  }
               ]
            },
            "expression_if_false":{
               "constant":0,
               "type":"constant"
            },
            "type":"conditional",
            "expression_if_true":{
               "constant":1,
               "type":"constant"
            }
         },
         "column_id":"no_of_separate_kitchen"
      },
      {
         "comment":null,
         "create_index":false,
         "display_name":"no_of_solid_waste_mgmt",
         "datatype":"integer",
         "expression":{
            "test":{
               "type":"and",
               "filters":[
                  {
                     "operator":"eq",
                     "type":"boolean_expression",
                     "expression":{
                        "string_expression":{
                           "type":"coalesce",
                           "expression":{
                              "datatype":null,
                              "type":"property_name",
                              "property_name":"type_of_waste_disposal"
                           },
                           "default_expression":{
                              "type":"constant",
                              "constant":"type_of_solid_waste_disposal_not_exists"
                           }
                        },
                        "delimiter":" ",
                        "type":"split_string",
                        "index_expression":{
                           "constant":0,
                           "type":"constant"
                        }
                     },
                     "comment":null,
                     "property_value":"solid"
                  },
                  {
                     "operator":"eq",
                     "type":"boolean_expression",
                     "expression":{
                        "datatype":"string",
                        "type":"property_name",
                        "property_name":"type"
                     },
                     "comment":null,
                     "property_value":"family"
                  }
               ]
            },
            "expression_if_true":{
               "type":"constant",
               "constant":1
            },
            "type":"conditional",
            "expression_if_false":{
               "type":"constant",
               "constant":0
            }
         },
         "transform":{

         },
         "is_primary_key":false,
         "is_nullable":true,
         "type":"expression",
         "column_id":"no_of_solid_waste_mgmt"
      },
      {
         "comment":null,
         "create_index":false,
         "display_name":"no_of_liquid_waste_mgmt",
         "datatype":"integer",
         "expression":{
            "test":{
               "type":"and",
               "filters":[
                  {
                     "type":"and",
                     "filters":[
                        {
                           "type":"or",
                           "filters":[
                              {
                                 "operator":"eq",
                                 "expression":{
                                    "string_expression":{
                                       "expression":{
                                          "datatype":null,
                                          "type":"property_name",
                                          "property_name":"type_of_waste_disposal"
                                       },
                                       "type":"coalesce",
                                       "default_expression":{
                                          "constant":"type_of_solid_waste_disposal_not_exists",
                                          "type":"constant"
                                       }
                                    },
                                    "delimiter":" ",
                                    "type":"split_string",
                                    "index_expression":{
                                       "type":"constant",
                                       "constant":0
                                    }
                                 },
                                 "type":"boolean_expression",
                                 "comment":null,
                                 "property_value":"liquid"
                              },
                              {
                                 "operator":"eq",
                                 "expression":{
                                    "string_expression":{
                                       "expression":{
                                          "datatype":null,
                                          "type":"property_name",
                                          "property_name":"type_of_waste_disposal"
                                       },
                                       "type":"coalesce",
                                       "default_expression":{
                                          "constant":"type_of_solid_waste_disposal_not_exists",
                                          "type":"constant"
                                       }
                                    },
                                    "delimiter":" ",
                                    "type":"split_string",
                                    "index_expression":{
                                       "type":"constant",
                                       "constant":1
                                    }
                                 },
                                 "type":"boolean_expression",
                                 "comment":null,
                                 "property_value":"liquid"
                              }
                           ]
                        },
                        {
                           "operator":"eq",
                           "type":"boolean_expression",
                           "expression":{
                              "datatype":"string",
                              "type":"property_name",
                              "property_name":"type"
                           },
                           "comment":null,
                           "property_value":"family"
                        }
                     ]
                  },
                  {
                     "operator":"eq",
                     "type":"boolean_expression",
                     "expression":{
                        "datatype":"string",
                        "type":"property_name",
                        "property_name":"type"
                     },
                     "comment":null,
                     "property_value":"family"
                  }
               ]
            },
            "expression_if_true":{
               "type":"constant",
               "constant":1
            },
            "type":"conditional",
            "expression_if_false":{
               "type":"constant",
               "constant":0
            }
         },
         "transform":{

         },
         "is_primary_key":false,
         "is_nullable":true,
         "type":"expression",
         "column_id":"no_of_liquid_waste_mgmt"
      },
      {
         "comment":null,
         "create_index":false,
         "display_name":null,
         "datatype":"integer",
         "type":"expression",
         "transform":{

         },
         "is_primary_key":false,
         "is_nullable":true,
         "expression":{
            "datatype":"integer",
            "test":{
               "type":"and",
               "filters":[
                  {
                     "operator":"eq",
                     "expression":{
                        "datatype":null,
                        "type":"property_name",
                        "property_name":"type"
                     },
                     "type":"boolean_expression",
                     "comment":null,
                     "property_value":"family"
                  },
                  {
                     "operator":"gt",
                     "expression":{
                        "type":"coalesce",
                        "expression":{
                           "datatype":"integer",
                           "type":"property_name",
                           "property_name":"llitn_currently_available"
                        },
                        "default_expression":{
                           "datatype":"integer",
                           "type":"constant",
                           "constant":0
                        }
                     },
                     "type":"boolean_expression",
                     "comment":null,
                     "property_value":0
                  }
               ]
            },
            "expression_if_false":{
               "constant":0,
               "type":"constant"
            },
            "type":"conditional",
            "expression_if_true":{
               "constant":1,
               "type":"constant"
            }
         },
         "column_id":"no_of_llitn_currently_available"
      }
   ],
 
   "base_item_expression":{

   },
 
   "configured_filter":{
      "type":"and",
      "filters":[
         {
            "operator":"eq",
            "type":"boolean_expression",
            "expression":{
               "datatype":null,
               "type":"property_name",
               "property_name":"closed"
            },
            "comment":null,
            "property_value":false
         },
         {
            "operator":"eq",
            "type":"boolean_expression",
            "expression":{
               "datatype":null,
               "type":"property_name",
               "property_name":"type"
            },
            "comment":null,
            "property_value":"family"
         }
      ]
   },
   
   "description":"",
   "referenced_doc_type":"CommCareCase",
   "display_name":"Household Profile Data Source",
   "table_id":"static-household_profile_data_source" 
}}