<?xml version='1.0' ?><pathfinder_followup xmlns="http://dev.commcarehq.org/Pathfinder/pathfinder_cc_follow_0.0.2a"><Meta><formName>PathfinderFollowUpVisit</formName><formVersion>0.0.1</formVersion><DeviceID>KRWP7R9SA48165FVSFFIB6575</DeviceID><CommCareVersion>0.0.6</CommCareVersion><TimeStart>2009-03-27T00:03:12.953</TimeStart><TimeEnd>2009-03-27T00:06:11.959</TimeEnd><username>dagila</username><chw_id>14</chw_id><uid>NFPL0YRQCAFRVBGKLP2KQT6TQ</uid></Meta><client_name> SAIDI MBWANA SELEMANI</client_name><client_number>1</client_number><type_of_client>HIV</type_of_client><client_available>1</client_available><referral>Aid_from_other_groups</referral><new_male_pcg>0</new_male_pcg><existing_male_pcg>1</existing_male_pcg><new_female_pcg>0</new_female_pcg><existing_female_pcg>1</existing_female_pcg><type_med>ARV</type_med><mosquito_net>1</mosquito_net><water_guard>1</water_guard><service_stopped>0</service_stopped></pathfinder_followup>