{
    "domains": [
      "fmoh-echis",
      "fmoh-echis-staging",
      "fmoh-echis-link-test"
    ],
    "server_environment": [
      "production",
      "echis"
    ],
    "report_id": "7_2_malaria_weekly_report",
    "data_source_table": "static_malaria_datasource",
    "config": {
      "title": "7.2 Malaria Weekly Report",
      "aggregation_columns":  [
        "region",
        "zone",
        "woreda",
        "health_center",
        "health_post",
        "report_week_date"
      ],
      "filters":  [
        {
          "datatype": "string",
          "choice_provider": {
            "include_descendants": true,
            "type": "location",
            "show_full_path": false
          },
          "show_all": true,
          "display": "Location",
          "field": "health_post_id",
          "ancestor_expression": {},
          "type": "dynamic_choice_list",
          "slug": "health_post_i"
        },
        {
          "compare_as_string": false,
          "required": false,
          "datatype": "string",
          "type": "dynamic_choice_list",
          "show_all": true,
          "display": "Reporting Week",
          "field": "report_week_date",
          "ancestor_expression": {},
          "choice_provider": {},
          "slug": "report_week_date"
        },
        {
          "compare_as_string": false,
          "datatype": "date",
          "required": false,
          "slug": "report_week_date_for_filter_gregorian",
          "field": "report_week_date_for_filter_gregorian",
          "type": "date",
          "display": "Report Week (for mobile)"
        },
        {
          "display": "Test or Real",
          "datatype": "string",
          "show_all": true,
          "choices": [
            {
              "display": "Test",
              "value": "Test"
            },
            {
              "display": "Real",
              "value": "Real"
            }
          ],
          "field": "test_or_real",
          "type": "choice_list",
          "slug": "test_or_real"
        },
        {
          "comment": null,
          "datatype": "string",
          "display": "region",
          "field": "region",
          "type": "dynamic_choice_list",
          "slug": "region"
        },
        {
          "comment": null,
          "datatype": "string",
          "display": "Zone",
          "field": "zone",
          "type": "dynamic_choice_list",
          "slug": "zone"
        },
        {
          "comment": null,
          "datatype": "string",
          "display": "Woreda",
          "field": "woreda",
          "type": "dynamic_choice_list",
          "slug": "woreda"
        },
        {
          "datatype": "string",
          "field": "health_center",
          "type": "dynamic_choice_list",
          "display": "Health Center",
          "slug": "health_center"
        },
        {
          "datatype": "string",
          "field": "health_post",
          "type": "dynamic_choice_list",
          "display": "Health Post",
          "slug": "health_post"
        },
        {
          "datatype": "string",
          "field": "illness_start_report_month",
          "type": "dynamic_choice_list",
          "display": "Report Month",
          "slug": "illness_start_report_month"
        }
      ] ,
      "columns":   [
        {
          "comment": null,
          "field": "region",
          "description": null,
          "format": "default",
          "css_class": null,
          "width": null,
          "aggregation": "simple",
          "column_id": "region",
          "visible": true,
          "transform": {},
          "calculate_total": false,
          "type": "field",
          "display": "Region"
        },
        {
          "comment": null,
          "field": "zone",
          "description": null,
          "format": "default",
          "css_class": null,
          "width": null,
          "aggregation": "simple",
          "column_id": "zone",
          "visible": true,
          "transform": {},
          "calculate_total": false,
          "type": "field",
          "display": "Zone"
        },
        {
          "comment": null,
          "field": "woreda",
          "description": null,
          "format": "default",
          "css_class": null,
          "width": null,
          "aggregation": "simple",
          "column_id": "woreda",
          "visible": true,
          "transform": {},
          "calculate_total": false,
          "type": "field",
          "display": "Woreda"
        },
        {
          "comment": null,
          "field": "health_center",
          "description": null,
          "format": "default",
          "css_class": null,
          "width": null,
          "aggregation": "simple",
          "column_id": "health_center",
          "visible": true,
          "transform": {},
          "calculate_total": false,
          "type": "field",
          "display": "Health Center"
        },
        {
          "comment": null,
          "field": "health_post",
          "description": null,
          "format": "default",
          "css_class": null,
          "width": null,
          "aggregation": "simple",
          "column_id": "health_post",
          "visible": true,
          "transform": {},
          "calculate_total": false,
          "type": "field",
          "display": "Health Post"
        },
        {
          "field": "report_week_date",
          "sortable": false,
          "description": null,
          "format": "default",
          "css_class": null,
          "transform": {},
          "column_id": "report_week_date",
          "visible": true,
          "display": "Reporting Week",
          "calculate_total": false,
          "type": "field",
          "width": null,
          "aggregation": "simple"
        },
        {
          "comment": "Total number of malaria case (or infection) in which the parasite has been detected in a diagnostic test, i.e. microscopy, a rapid diagnostic test or a molecular diagnostic test",
          "field": "confirmed_malaria_cases_ftat",
          "description": "Total number of malaria case (or infection) in which the parasite has been detected in a diagnostic test, i.e. microscopy, a rapid diagnostic test or a molecular diagnostic test",
          "format": "default",
          "css_class": null,
          "width": null,
          "aggregation": "sum",
          "column_id": "confirmed_malaria_cases_ftat",
          "visible": true,
          "transform": {},
          "calculate_total": false,
          "type": "field",
          "display": "Confirmed Malaria Cases Ftat"
        },
        {
          "comment": "Number of malaria case (or infection) in which the parasite has been detected in a diagnostic test within the jurisdiction of the health post",
          "field": "confirmed_malaria_cases_hp",
          "description": "Number of malaria case (or infection) in which the parasite has been detected in a diagnostic test within the jurisdiction of the health post",
          "format": "default",
          "css_class": null,
          "width": null,
          "aggregation": "sum",
          "column_id": "confirmed_malaria_cases_hp",
          "visible": true,
          "transform": {},
          "calculate_total": false,
          "type": "field",
          "display": "Confirmed Malaria Cases Hp"
        },
        {
          "comment": "Number of index case households and those demarcated from the index case house within 70m radius or nearest five households where houses densely clustered and visited",
          "field": "households_investigated",
          "description": "Number of index case households and those demarcated from the index case house within 70m radius or nearest five households where houses densely clustered and visited",
          "format": "default",
          "css_class": null,
          "width": null,
          "aggregation": "sum",
          "column_id": "households_investigated",
          "visible": true,
          "transform": {},
          "calculate_total": false,
          "type": "field",
          "display": "Households Investigated"
        },
        {
          "comment": "Number of individuals listed in the investigated index case and neighboring households and entitled for finger prick except index cases, < 6 months infants, and sever malaria cases",
          "field": "entitled_for_finger_prick",
          "description": "Number of individuals listed in the investigated index case and neighboring households and entitled for finger prick except index cases, < 6 months infants, and sever malaria cases",
          "format": "default",
          "css_class": null,
          "width": null,
          "aggregation": "sum",
          "column_id": "entitled_for_finger_prick",
          "visible": true,
          "transform": {},
          "calculate_total": false,
          "type": "field",
          "display": "Entitled For Finger Prick"
        },
        {
          "comment": "Number of individuals listed in the investigated index case and neighboring households whom received finger prick",
          "field": "received_finger_prick",
          "description": "Number of individuals listed in the investigated index case and neighboring households whom received finger prick",
          "format": "default",
          "css_class": null,
          "width": null,
          "aggregation": "sum",
          "column_id": "received_finger_prick",
          "visible": true,
          "transform": {},
          "calculate_total": false,
          "type": "field",
          "display": "Received Finger Prick"
        },
        {
          "comment": "Number of confirmed malaria cases/infections reported during case investigation",
          "field": "confirmed_malaria_cases",
          "description": "Number of confirmed malaria cases/infections reported during case investigation",
          "format": "default",
          "css_class": null,
          "width": null,
          "aggregation": "sum",
          "column_id": "confirmed_malaria_cases",
          "visible": true,
          "transform": {},
          "calculate_total": false,
          "type": "field",
          "display": "Confirmed Malaria Cases"
        },
        {
          "comment": "Number of confirmed malaria cases/infections reported as plasmodium falciparium during case investigation",
          "field": "confirmed_malaria_cases_plasmodium_falciparium",
          "description": "Number of confirmed malaria cases/infections reported as plasmodium falciparium during case investigation",
          "format": "default",
          "css_class": null,
          "width": null,
          "aggregation": "sum",
          "column_id": "confirmed_malaria_cases_plasmodium_falciparium",
          "visible": true,
          "transform": {},
          "calculate_total": false,
          "type": "field",
          "display": "Confirmed Malaria Cases Plasmodium Falciparium"
        },
        {
          "comment": "Number of confirmed malaria cases/infections reported as plasmodium vivax during case investigation",
          "field": "confirmed_malaria_cases_plasmodium_vivax",
          "description": "Number of confirmed malaria cases/infections reported as plasmodium vivax during case investigation",
          "format": "default",
          "css_class": null,
          "width": null,
          "aggregation": "sum",
          "column_id": "confirmed_malaria_cases_plasmodium_vivax",
          "visible": true,
          "transform": {},
          "calculate_total": false,
          "type": "field",
          "display": "Confirmed Malaria Cases Plasmodium Vivax"
        },
        {
          "comment": "Number of confirmed malaria cases/infections reported as mixed (pf/pv) during case investigation",
          "field": "confirmed_malaria_cases_mixed",
          "description": "Number of confirmed malaria cases/infections reported as mixed (pf/pv) during case investigation",
          "format": "default",
          "css_class": null,
          "width": null,
          "aggregation": "sum",
          "column_id": "confirmed_malaria_cases_mixed",
          "visible": true,
          "transform": {},
          "calculate_total": false,
          "type": "field",
          "display": "Confirmed Malaria Cases Mixed"
        },
        {
          "comment": "Confirmed malaria case or infection in which the infection was acquired outside the area in s/he lives",
          "field": "Cases_with_travel_history",
          "description": "Confirmed malaria case or infection in which the infection was acquired outside the area in s/he lives",
          "format": "default",
          "css_class": null,
          "width": null,
          "aggregation": "sum",
          "column_id": "Cases_with_travel_history",
          "visible": true,
          "transform": {},
          "calculate_total": false,
          "type": "field",
          "display": "Cases With Travel History"
        },
        {
          "comment": "Confirmed malaria case or infection contracted locally with no evidence of importation",
          "field": "Cases_without_travel_history",
          "description": "Confirmed malaria case or infection contracted locally with no evidence of importation",
          "format": "default",
          "css_class": null,
          "width": null,
          "aggregation": "sum",
          "column_id": "Cases_without_travel_history",
          "visible": true,
          "transform": {},
          "calculate_total": false,
          "type": "field",
          "display": "Cases Without Travel History"
        },
        {
          "comment": "Number of households sprayed",
          "field": "Number_of_households_sprayed",
          "description": "Number of households sprayed",
          "format": "default",
          "css_class": null,
          "width": null,
          "aggregation": "sum",
          "column_id": "Number_of_households_sprayed",
          "visible": true,
          "transform": {},
          "calculate_total": false,
          "type": "field",
          "display": "Number Of Households Sprayed"
        },
        {
          "comment": "Number of people protected because of chemical spray",
          "field": "number_people_protected_by_chemical_spray",
          "description": "Number of people protected because of chemical spray",
          "format": "default",
          "css_class": null,
          "width": null,
          "aggregation": "sum",
          "column_id": "number_people_protected_by_chemical_spray",
          "visible": true,
          "transform": {},
          "calculate_total": false,
          "type": "field",
          "display": "Number People Protected By Chemical Spray"
        },
        {
          "comment": "Amount of chemical used in kg",
          "field": "chemical_used_in_kg",
          "description": "Amount of chemical used in kg",
          "format": "default",
          "css_class": null,
          "width": null,
          "aggregation": "sum",
          "column_id": "chemical_used_in_kg",
          "visible": true,
          "transform": {},
          "calculate_total": false,
          "type": "field",
          "display": "Chemical Used In Kg"
        },
        {
          "comment": "Number of visited households on bednet usage",
          "field": "bednet_usage",
          "description": "Number of visited households on bednet usage",
          "format": "default",
          "css_class": null,
          "width": null,
          "aggregation": "sum",
          "column_id": "bednet_usage",
          "visible": true,
          "transform": {},
          "calculate_total": false,
          "type": "field",
          "display": "Bednet Usage"
        },
        {
          "comment": "Number of visited households who have properly used their bednet",
          "field": "llitn_properly_used",
          "description": "Number of visited households who have properly used their bednet",
          "format": "default",
          "css_class": null,
          "width": null,
          "aggregation": "sum",
          "column_id": "llitn_properly_used",
          "visible": true,
          "transform": {},
          "calculate_total": false,
          "type": "field",
          "display": "Llitn Properly Used"
        },
        {
          "comment": "Number of clients suspected for malaria, and tested with RDT",
          "field": "suspected_and_tested_with_rdt",
          "description": "Number of clients suspected for malaria, and tested with RDT",
          "format": "default",
          "css_class": null,
          "width": null,
          "aggregation": "sum",
          "column_id": "suspected_and_tested_with_rdt",
          "visible": true,
          "transform": {},
          "calculate_total": false,
          "type": "field",
          "display": "Suspected And Tested With Rdt"
        },
        {
          "comment": "Total Malaria Cases Confirmed by RDT",
          "field": "Total_Malaria_Cases_Confirmed_RDT",
          "description": "Total Malaria Cases Confirmed by RDT",
          "format": "default",
          "css_class": null,
          "width": null,
          "aggregation": "sum",
          "column_id": "Total_Malaria_Cases_Confirmed_RDT",
          "visible": true,
          "transform": {},
          "calculate_total": false,
          "type": "field",
          "display": "Total Malaria Cases Confirmed Rdt"
        },
        {
          "comment": "RDT Confirmed Malaria Cases by Plasmodium Species- P. Falciparum",
          "field": "RDT_Confirmed_Malaria_Cases_pf",
          "description": "RDT Confirmed Malaria Cases by Plasmodium Species- P. Falciparum",
          "format": "default",
          "css_class": null,
          "width": null,
          "aggregation": "sum",
          "column_id": "RDT_Confirmed_Malaria_Cases_pf",
          "visible": true,
          "transform": {},
          "calculate_total": false,
          "type": "field",
          "display": "Rdt Confirmed Malaria Cases Pf"
        },
        {
          "comment": "RDT Confirmed Malaria Cases by Plasmodium Species- P. Vivax",
          "field": "RDT_Confirmed_Malaria_Cases_pv",
          "description": "RDT Confirmed Malaria Cases by Plasmodium Species- P. Vivax",
          "format": "default",
          "css_class": null,
          "width": null,
          "aggregation": "sum",
          "column_id": "RDT_Confirmed_Malaria_Cases_pv",
          "visible": true,
          "transform": {},
          "calculate_total": false,
          "type": "field",
          "display": "Rdt Confirmed Malaria Cases Pv"
        },
        {
          "comment": "Total Malaria Cases by Age Category- Under 5 years",
          "field": "Malaria_Cases_under_5",
          "description": "Total Malaria Cases by Age Category- Under 5 years",
          "format": "default",
          "css_class": null,
          "width": null,
          "aggregation": "sum",
          "column_id": "Malaria_Cases_under_5",
          "visible": true,
          "transform": {},
          "calculate_total": false,
          "type": "field",
          "display": "Malaria Cases Under 5"
        },
        {
          "comment": "Total Malaria Cases by Age Category- From 5 to 14 years",
          "field": "Malaria_Cases_5_to_14",
          "description": "Total Malaria Cases by Age Category- From 5 to 14 years",
          "format": "default",
          "css_class": null,
          "width": null,
          "aggregation": "sum",
          "column_id": "Malaria_Cases_5_to_14",
          "visible": true,
          "transform": {},
          "calculate_total": false,
          "type": "field",
          "display": "Malaria Cases 5 To 14"
        },
        {
          "comment": "Total Malaria Cases by Age Category- over 15 years",
          "field": "Malaria_Cases_over_15",
          "description": "Total Malaria Cases by Age Category- over 15 years",
          "format": "default",
          "css_class": null,
          "width": null,
          "aggregation": "sum",
          "column_id": "Malaria_Cases_over_15",
          "visible": true,
          "transform": {},
          "calculate_total": false,
          "type": "field",
          "display": "Malaria Cases Over 15"
        },
        {
          "comment": "Pregant mothers with positive malaria cases",
          "field": "Positive_Pregant_mothers",
          "description": "Pregant mothers with positive malaria cases",
          "format": "default",
          "css_class": null,
          "width": null,
          "aggregation": "sum",
          "column_id": "Positive_Pregant_mothers",
          "visible": true,
          "transform": {},
          "calculate_total": false,
          "type": "field",
          "display": "Positive Pregant Mothers"
        },
        {
          "comment": "Number of index households and those demarcated from the index case house within 70m radius or nearest five households where houses densely clustered.",
          "field": "households_eligible_delineated_for_investigation",
          "description": "Number of index households and those demarcated from the index case house within 70m radius or nearest five households where houses densely clustered.",
          "format": "default",
          "css_class": null,
          "width": null,
          "aggregation": "sum",
          "column_id": "households_eligible_delineated_for_investigation",
          "visible": true,
          "transform": {},
          "calculate_total": false,
          "type": "field",
          "display": "Households Eligible Delineated For Investigation"
        },
        {
          "comment": "Number of individuals living in the index case and neighboring households including visitors listed during case investigated",
          "field": "individuals_living_in_index_case",
          "description": "Number of individuals living in the index case and neighboring households including visitors listed during case investigated",
          "format": "default",
          "css_class": null,
          "width": null,
          "aggregation": "sum",
          "column_id": "individuals_living_in_index_case",
          "visible": true,
          "transform": {},
          "calculate_total": false,
          "type": "field",
          "display": "Individuals Living In Index Case"
        }
      ]
    }
  }
  