<?xml version='1.0' ?><pathfinder_registration xmlns="http://dev.commcarehq.org/Pathfinder/pathfinder_cc_registration_0.0.2a"><Meta><formName>PathfinderRegistratonVisit</formName><formVersion>0.01</formVersion><DeviceID>NF7D9Q0EMV3ISJO47QLJCIZA4</DeviceID><TimeStart>2009-04-23T07:46:40.400</TimeStart><TimeEnd>2009-04-23T07:59:16.424</TimeEnd><username>rajabu</username><chw_id>12</chw_id><uid>4KN6QQBMWA04ATRJMUFKLBLYS</uid></Meta><patient><region>Dar-es-Salaam</region><district>Temeke</district><ward>TOANGOMA</ward><village>VIKUNAI</village><family_name>KAMPAMBE</family_name><given_name>KASIMU </given_name><middle_name>HEMEDI</middle_name><date_of_birth>1968-08-14</date_of_birth><client_number>9</client_number><sex>M</sex><marital_status>divorced</marital_status><children_under_18>2</children_under_18><education>Primary</education><religion>Mulism</religion><occupation>Self_Employed</occupation><status>Chronic_Ill</status><type_of_client /><hiv_tested>Yes</hiv_tested><type_med>Septrini Local_medicine</type_med><existing_female_pcg>1</existing_female_pcg><existing_male_pcg>1</existing_male_pcg><mosquito_net>No</mosquito_net><water_guard>No</water_guard><remarks>ANAHITAJI KUTEMBELEWA</remarks></patient></pathfinder_registration>