{
  "domains": [
    "icds-dashboard-qa",
    "laurence-project-1",
    "jessica-icds-cas",
    "marissa-test",
    "derek-icds-sandbox",
    "priyanka-app",
    "shrena-dev",
    "aparatest",
    "reach-sandbox",
    "reach-dashboard-qa",
    "reach-test",
    "icds-cas",
    "cas-lab"
  ],
  "server_environment": [
    "staging",
    "icds"
  ],
  "mirrored_engine_ids": [
    {
      "server_environment": "icds",
      "engine_ids": ["icds-ucr-citus"]
    },
    {
      "server_environment": "staging",
      "engine_ids": ["icds-ucr-citus"]
    }
  ],
  "config": {
    "table_id": "static-dashboard_birth_preparedness_forms",
    "display_name": "Forms - Birth Preparedness Forms for Dashboard",
    "referenced_doc_type": "XFormInstance",
    "description": "Birth Preparedness form data for the dashboard",
    "base_item_expression": {},
    "configured_filter": {
      "type": "boolean_expression",
      "operator": "eq",
      "expression": {
        "type": "property_name",
        "property_name": "xmlns"
      },
      "property_value": "http://openrosa.org/formdesigner/2864010F-B1B1-4711-8C59-D5B2B81D65DB"
    },
    "validations": [
      {
        "name": "submitted_by_aww",
        "error_message": "Form not submitted by AWW",
        "expression": {
          "type": "boolean_expression",
          "operator": "eq",
          "expression": {
            "location_id_expression": {
              "type": "named",
              "name": "user_location_id"
            },
            "type": "location_type_name"
          },
          "property_value": "awc"
        }
      }
    ],
    "configured_indicators": [
      {
        "column_id": "timeend",
        "display_name": null,
        "datatype": "datetime",
        "type": "expression",
        "expression": {
          "datatype": "date",
          "type": "property_path",
          "property_path": [
            "form",
            "meta",
            "timeEnd"
          ]
        }
      },
      {
        "column_id": "state_id",
        "datatype": "string",
        "type": "expression",
        "expression": {
          "type": "ancestor_location",
          "location_id": {
            "type": "named",
            "name": "user_location_id"
          },
          "location_type": "state",
          "location_property": "_id"
        },
        "create_index": true
      },
      {
        "display_name": "Supervisor ID",
        "datatype": "string",
        "column_id": "supervisor_id",
        "is_primary_key": true,
        "is_nullable": false,
        "type": "expression",
        "expression": {
          "type": "ancestor_location",
          "location_id": {
            "type": "named",
            "name": "user_location_id"
          },
          "location_type": "supervisor",
          "location_property": "_id"
        }
      },
      {
        "column_id": "received_on",
        "datatype": "datetime",
        "type": "expression",
        "expression": {
          "type": "property_name",
          "datatype": "datetime",
          "property_name": "received_on"
        }
      },
      {
        "column_id": "ccs_record_case_id",
        "datatype": "string",
        "type": "expression",
        "expression": {
          "type": "property_path",
          "property_path": ["form", "case_load_ccs_record0", "case", "@case_id"]
        }
      },
      {
        "column_id": "immediate_breastfeeding",
        "datatype": "small_integer",
        "type": "expression",
        "expression": {
          "type": "icds_boolean",
          "boolean_property": {
            "type": "property_path",
            "property_path": ["form", "bp2", "immediate_breastfeeding"]
          },
          "true_values": ["yes"],
          "false_values": ["no"]
        }
      },
      {
        "column_id": "using_ifa",
        "datatype": "small_integer",
        "type": "expression",
        "expression": {
          "type": "icds_boolean",
          "boolean_property": {
            "type": "property_path",
            "property_path": ["form", "bp1", "using_ifa"]
          },
          "true_values": ["yes"],
          "false_values": ["no"]
        }
      },
      {
        "column_id": "play_birth_preparedness_vid",
        "datatype": "small_integer",
        "type": "expression",
        "expression": {
          "type": "icds_boolean",
          "boolean_property": {
            "type": "property_path",
            "property_path": ["form", "bp2", "play_birth_preparedness_vid"]
          },
          "true_values": ["yes"],
          "false_values": ["no"]
        }
      },
      {
        "column_id": "counsel_preparation",
        "datatype": "small_integer",
        "type": "expression",
        "expression": {
          "type": "icds_boolean",
          "boolean_property": {
            "type": "property_path",
            "property_path": ["form", "bp2", "counsel_preparation"]
          },
          "true_values": ["yes"],
          "false_values": ["no"]
        }
      },
      {
        "column_id": "play_family_planning_vid",
        "datatype": "small_integer",
        "type": "expression",
        "expression": {
          "type": "icds_boolean",
          "boolean_property": {
            "type": "property_path",
            "property_path": ["form", "play_family_planning_vid"]
          },
          "true_values": ["yes"],
          "false_values": ["no"]
        }
      },
      {
        "column_id": "conceive",
        "datatype": "small_integer",
        "type": "expression",
        "expression": {
          "type": "icds_boolean",
          "boolean_property": {
            "type": "property_path",
            "property_path": ["form", "conceive"]
          },
          "true_values": ["yes"],
          "false_values": ["no"]
        }
      },
      {
        "column_id": "counsel_accessible_ppfp",
        "datatype": "small_integer",
        "type": "expression",
        "expression": {
          "type": "icds_boolean",
          "boolean_property": {
            "type": "property_path",
            "property_path": ["form", "family_planning_group", "counsel_accessible_ppfp"]
          },
          "true_values": ["yes"],
          "false_values": ["no"]
        }
      },
      {
        "column_id": "anemia",
        "datatype": "small_integer",
        "type": "expression",
        "expression": {
          "type": "switch",
          "switch_on": {
            "type": "property_path",
            "property_path": ["form", "bp1", "anemia"]
          },
          "cases": {
            "severe": {
              "type": "constant",
              "constant": 1
            },
            "moderate": {
              "type": "constant",
              "constant": 2
            },
            "normal": {
              "type": "constant",
              "constant": 3
            }
          },
          "default": {
            "type": "constant",
            "constant": 0
          }
        }
      },
      {
        "column_id": "ifa_last_seven_days",
        "datatype": "small_integer",
        "type": "expression",
        "expression": {
          "type": "property_path",
          "property_path": ["form", "bp1", "ifa_last_seven_days"]
        }
      },
      {
        "column_id": "eating_extra",
        "datatype": "small_integer",
        "type": "expression",
        "expression": {
          "type": "icds_boolean",
          "boolean_property": {
            "type": "property_path",
            "property_path": ["form", "bp1", "eating_extra"]
          },
          "true_values": ["yes"],
          "false_values": ["no"]
        }
      },
      {
        "column_id": "resting",
        "datatype": "small_integer",
        "type": "expression",
        "expression": {
          "type": "icds_boolean",
          "boolean_property": {
            "type": "property_path",
            "property_path": ["form", "bp1", "resting"]
          },
          "true_values": ["yes"],
          "false_values": ["no"]
        }
      },
      {
        "column_id": "anc_weight",
        "datatype": "small_integer",
        "type": "expression",
        "expression": {
          "type": "nested",
          "argument_expression": {
            "type": "named",
            "name": "anc_details"
          },
          "value_expression": {
            "type": "property_name",
            "property_name": "anc_weight"
          }
        }
      },
      {
        "column_id": "anc_blood_pressure",
        "datatype": "small_integer",
        "type": "expression",
        "expression": {
          "type": "switch",
          "switch_on": {
            "type": "nested",
            "argument_expression": {
              "type": "named",
              "name": "anc_details"
            },
            "value_expression": {
              "type": "property_name",
              "property_name": "anc_blood_pressure"
            }
          },
          "cases": {
            "normal": {
              "type": "constant",
              "constant": 1
            },
            "high": {
              "type": "constant",
              "constant": 2
            },
            "not_measured": {
              "type": "constant",
              "constant": 3
            }
          },
          "default": {
            "type": "constant",
            "constant": 0
          }
        }
      },
      {
        "column_id": "bp_sys",
        "datatype": "small_integer",
        "type": "expression",
        "expression": {
          "type": "nested",
          "argument_expression": {
            "type": "named",
            "name": "anc_details"
          },
          "value_expression": {
            "type": "property_name",
            "property_name": "bp_sys"
          }
        }
      },
      {
        "column_id": "bp_dia",
        "datatype": "small_integer",
        "type": "expression",
        "expression": {
          "type": "nested",
          "argument_expression": {
            "type": "named",
            "name": "anc_details"
          },
          "value_expression": {
            "type": "property_name",
            "property_name": "bp_dias"
          }
        }
      },
      {
        "column_id": "anc_abnormalities",
        "datatype": "small_integer",
        "type": "expression",
        "expression": {
          "type": "icds_boolean",
          "boolean_property": {
            "type": "nested",
            "argument_expression": {
              "type": "named",
              "name": "anc_details"
            },
            "value_expression": {
              "type": "property_name",
              "property_name": "anc_abnormalities"
            }
          },
          "true_values": ["yes"],
          "false_values": ["no"]
        }
      },
      {
        "column_id": "anc_hemoglobin",
        "datatype": "decimal",
        "type": "expression",
        "expression": {
          "type": "nested",
          "argument_expression": {
            "type": "named",
            "name": "anc_details"
          },
          "value_expression": {
            "type": "property_name",
            "property_name": "anc_hemoglobin"
          }
        }
      },
      {
        "column_id": "bleeding",
        "datatype": "small_integer",
        "type": "expression",
        "expression": {
          "type": "icds_boolean",
          "boolean_property": {
            "type": "property_path",
            "property_path": ["form", "bp2", "bleeding"]
          },
          "true_values": ["yes"],
          "false_values": ["no"]
        }
      },
      {
        "column_id": "swelling",
        "datatype": "small_integer",
        "type": "expression",
        "expression": {
          "type": "icds_boolean",
          "boolean_property": {
            "type": "property_path",
            "property_path": ["form", "bp2", "swelling"]
          },
          "true_values": ["yes"],
          "false_values": ["no"]
        }
      },
      {
        "column_id": "blurred_vision",
        "datatype": "small_integer",
        "type": "expression",
        "expression": {
          "type": "icds_boolean",
          "boolean_property": {
            "type": "property_path",
            "property_path": ["form", "bp2", "blurred_vision"]
          },
          "true_values": ["yes"],
          "false_values": ["no"]
        }
      },
      {
        "column_id": "convulsions",
        "datatype": "small_integer",
        "type": "expression",
        "expression": {
          "type": "icds_boolean",
          "boolean_property": {
            "type": "property_path",
            "property_path": ["form", "bp2", "convulsions"]
          },
          "true_values": ["yes"],
          "false_values": ["no"]
        }
      },
      {
        "column_id": "rupture",
        "datatype": "small_integer",
        "type": "expression",
        "expression": {
          "type": "icds_boolean",
          "boolean_property": {
            "type": "property_path",
            "property_path": ["form", "bp2", "rupture"]
          },
          "true_values": ["yes"],
          "false_values": ["no"]
        }
      },
      {
        "column_id": "unscheduled_visit",
        "datatype": "small_integer",
        "type": "expression",
        "expression": {
          "type": "property_path",
          "property_path": ["form", "unscheduled_visit"]
        }
      },
      {
        "column_id": "days_visit_late",
        "datatype": "small_integer",
        "type": "expression",
        "expression": {
          "type": "property_path",
          "property_path": ["form", "days_visit_late"]
        }
      },
      {
        "column_id": "next_visit",
        "datatype": "date",
        "type": "expression",
        "expression": {
          "type": "property_path",
          "property_path": ["form", "next_due"]
        }
      }
    ],
    "named_expressions": {
      "user_location_id": {
        "type": "icds_user_location",
        "user_id_expression": {
          "type": "property_path",
          "property_path": ["form", "meta", "userID"]
        }
      },
      "anc_details": {
        "type": "nested",
        "argument_expression": {
          "type": "array_index",
          "array_expression": {
            "type": "filter_items",
            "items_expression": {
	          "type": "property_path",
	          "property_path": ["form", "bp1", "iteration", "item"]
            },
            "filter_expression": {
              "type": "not",
              "filter": {
                "type": "boolean_expression",
                "expression": {
                  "type": "property_path",
                  "property_path": ["filter", "anc_details"]
                },
                "operator": "in",
                "property_value": ["", null]
              }
            }
          },
          "index_expression": {
            "type": "constant",
            "constant": 0
          }
        },
        "value_expression": {
          "type": "property_path",
          "property_path": ["filter", "anc_details"]
        }
      }
    },
    "named_filters": {},
    "engine_id": "icds-ucr",
    "sql_settings": {
      "citus_config": {
        "distribution_type": "hash",
        "distribution_column": "supervisor_id"
      },
      "primary_key": ["supervisor_id","doc_id"]
    },
    "disable_destructive_rebuild": true
  }
}
